{ 
    
    "madra_prison": [
        {
            "shape": [ 24,52, 0,1, 39,41, 38,53 ]
        },
        {
            "shape": [ 104,183, 89,199, 89,185 ]
        },
        {
            "shape": [ 37,184, 0,201, 22,169, 37,171 ]
        },
        {
            "shape": [ 55,199, 0,201, 37,184, 55,185 ]
        },
        {
            "shape": [ 198,38, 240,1, 217,54, 200,52 ]
        },
        {
            "shape": [ 218,149, 239,199, 203,169, 205,155 ]
        },
        {
            "shape": [ 24,116, 21,83, 104,81, 104,118 ]
        },
        {
            "shape": [ 138,82, 217,83, 216,117, 137,117 ]
        },
        {
            "shape": [ 127,153, 133,162, 134,170, 104,183, 106,162, 112,153 ]
        },
        {
            "shape": [ 105,40, 135,37, 136,125, 106,125 ]
        },
        {
            "shape": [ 0,201, 0,1, 21,83, 24,116, 22,169 ]
        },
        {
            "shape": [ 134,170, 203,169, 239,199, 89,199, 104,183 ]
        },
        {
            "shape": [ 218,149, 216,117, 217,83, 240,1, 239,199 ]
        },
        {
            "shape": [ 217,54, 240,1, 217,83 ]
        },
        {
            "shape": [ 135,37, 0,1, 240,1, 198,38 ]
        },
        {
            "shape": [ 105,40, 39,41, 0,1, 135,37 ]
        },
        {
            "shape": [ 21,83, 0,1, 24,52 ]
        },
        {
            "shape": [ 192,169, 183,165, 187,153, 199,156 ]
        }
    ]
}
